{
  "slug": "health-check",
  "runtimes": {
    "node": {
      "frameworks": {
        "express": {
          "dependencies": {
            "runtime": [
              "dotenv-flow",
              "cross-env"
            ],
            "dev": []
          },
          "env": [
            "PORT"
          ],
          "architectures": {
            "mvc": {
              "files": [
                {
                  "type": "file",
                  "path": "src/app.test.ts",
                  "content": "import express, { type Application } from \"express\";\r\n// import \"dotenv/config\";\r\nimport healthRoutes from \"./routes/health.routes\";\r\n\r\nconst app: Application = express();\r\n\r\napp.use(express.json());\r\n\r\n// Health check routes\r\napp.use(\"/api/v1/health\", healthRoutes);\r\n\r\n// Other routes here\r\n// ...\r\n\r\nconst PORT = process.env.PORT || 6000;\r\n\r\napp.listen(PORT, () => {\r\n  console.log(`Server is running on http://localhost:${PORT}`);\r\n});\r\n"
                },
                {
                  "type": "file",
                  "path": "src/routes/health.routes.ts",
                  "content": "import { Router } from \"express\";\r\nimport {\r\n  healthCheck,\r\n  detailedHealthCheck\r\n} from \"../controllers/health.controller\";\r\n\r\nconst router = Router();\r\n\r\nrouter.get(\"/\", healthCheck);\r\nrouter.get(\"/detailed\", detailedHealthCheck);\r\n\r\nexport default router;\r\n"
                },
                {
                  "type": "file",
                  "path": "src/controllers/health.controller.ts",
                  "content": "import { Request, Response } from \"express\";\r\nimport { ApiResponse } from \"../utils/api-response\";\r\n\r\n/**\r\n * Basic health check endpoint\r\n * GET /api/health\r\n */\r\nexport const healthCheck = async (_req: Request, res: Response) => {\r\n  return ApiResponse.Success(res, \"Service is healthy\", {\r\n    status: \"healthy\",\r\n    timestamp: new Date().toISOString(),\r\n    uptime: process.uptime()\r\n  });\r\n};\r\n\r\n/**\r\n * Detailed health check with system information\r\n * GET /api/health/detailed\r\n */\r\nexport const detailedHealthCheck = async (_req: Request, res: Response) => {\r\n  const healthData = {\r\n    status: \"healthy\",\r\n    timestamp: new Date().toISOString(),\r\n    uptime: process.uptime(),\r\n    environment: process.env.NODE_ENV || \"development\",\r\n    version: process.env.npm_package_version || \"1.0.0\",\r\n    memory: {\r\n      used:\r\n        Math.round((process.memoryUsage().heapUsed / 1024 / 1024) * 100) / 100,\r\n      total:\r\n        Math.round((process.memoryUsage().heapTotal / 1024 / 1024) * 100) / 100,\r\n      unit: \"MB\"\r\n    },\r\n    cpu: {\r\n      usage: process.cpuUsage()\r\n    }\r\n  };\r\n\r\n  return ApiResponse.Success(res, \"Service is healthy\", healthData);\r\n};\r\n"
                },
                {
                  "type": "file",
                  "path": "src/utils/api-response.ts",
                  "content": "import { STATUS_CODES, StatusCode } from \"../constants/status-codes\";\r\nimport type { Response } from \"express\";\r\n\r\ntype ApiResponseParams<T> = {\r\n  success: boolean;\r\n  message: string;\r\n  statusCode: StatusCode;\r\n  data?: T | null;\r\n  errors?: unknown;\r\n};\r\n\r\nexport class ApiResponse<T = unknown> {\r\n  public readonly success: boolean;\r\n  public readonly message: string;\r\n  public readonly statusCode: StatusCode;\r\n  public readonly data?: T | null;\r\n  public readonly errors?: unknown;\r\n\r\n  constructor({\r\n    success,\r\n    message,\r\n    statusCode,\r\n    data = null,\r\n    errors\r\n  }: ApiResponseParams<T>) {\r\n    this.success = success;\r\n    this.message = message;\r\n    this.statusCode = statusCode;\r\n    this.data = data;\r\n    this.errors = errors;\r\n  }\r\n\r\n  send(res: Response): Response {\r\n    return res.status(this.statusCode).json({\r\n      success: this.success,\r\n      message: this.message,\r\n      statusCode: this.statusCode,\r\n      ...(this.data !== undefined && { data: this.data }),\r\n      ...(this.errors !== undefined && { errors: this.errors })\r\n    });\r\n  }\r\n\r\n  static Success<T>(\r\n    res: Response,\r\n    message: string,\r\n    data?: T,\r\n    statusCode: StatusCode = STATUS_CODES.OK\r\n  ): Response {\r\n    return new ApiResponse<T>({\r\n      success: true,\r\n      message,\r\n      data,\r\n      statusCode\r\n    }).send(res);\r\n  }\r\n\r\n  static ok<T>(res: Response, message = \"OK\", data?: T) {\r\n    return ApiResponse.Success(res, message, data, STATUS_CODES.OK);\r\n  }\r\n\r\n  static created<T>(res: Response, message = \"Created\", data?: T) {\r\n    return ApiResponse.Success(res, message, data, STATUS_CODES.CREATED);\r\n  }\r\n}\r\n\r\n/*\r\n * Usage:\r\n * ApiResponse.ok(res, \"OK\", data);\r\n * ApiResponse.created(res, \"Created\", data);\r\n */\r\n"
                },
                {
                  "type": "file",
                  "path": "src/constants/status-codes.ts",
                  "content": "export const STATUS_CODES = {\r\n  // 2xx Success\r\n  OK: 200,\r\n  CREATED: 201,\r\n  ACCEPTED: 202,\r\n  NO_CONTENT: 204,\r\n\r\n  // 3xx Redirection\r\n  MOVED_PERMANENTLY: 301,\r\n  FOUND: 302,\r\n  NOT_MODIFIED: 304,\r\n\r\n  // 4xx Client Errors\r\n  BAD_REQUEST: 400,\r\n  UNAUTHORIZED: 401,\r\n  FORBIDDEN: 403,\r\n  NOT_FOUND: 404,\r\n  CONFLICT: 409,\r\n  UNPROCESSABLE_ENTITY: 422,\r\n  TOO_MANY_REQUESTS: 429,\r\n\r\n  // 5xx Server Errors\r\n  INTERNAL_SERVER_ERROR: 500,\r\n  NOT_IMPLEMENTED: 501,\r\n  BAD_GATEWAY: 502,\r\n  SERVICE_UNAVAILABLE: 503,\r\n  GATEWAY_TIMEOUT: 504\r\n} as const;\r\n\r\nexport type StatusCode = (typeof STATUS_CODES)[keyof typeof STATUS_CODES];\r\n"
                }
              ]
            },
            "feature": {
              "files": [
                {
                  "type": "file",
                  "path": "src/app.test.ts",
                  "content": "import express, { type Application } from \"express\";\r\nimport \"dotenv-flow/config\";\r\nimport Routes from \"./routes\";\r\n\r\nconst app: Application = express();\r\n\r\napp.use(express.json());\r\n\r\n// Health check routes\r\napp.use(\"/api\", Routes);\r\n\r\n// Other routes here\r\n// ...\r\n\r\nconst PORT = process.env.PORT || 6000;\r\n\r\napp.listen(PORT, () => {\r\n  console.log(`Server is running on http://localhost:${PORT}`);\r\n});\r\n"
                },
                {
                  "type": "file",
                  "path": "src/routes/index.ts",
                  "content": "import { Router } from \"express\";\r\nimport HealthRouter from \"../modules/health/health.routes\";\r\n\r\nconst router = Router();\r\n\r\nrouter.use(\"/v1/health\", HealthRouter);\r\n\r\nexport default router;\r\n"
                },
                {
                  "type": "file",
                  "path": "src/shared/constants/status-codes.ts",
                  "content": "export const STATUS_CODES = {\r\n  // 2xx Success\r\n  OK: 200,\r\n  CREATED: 201,\r\n  ACCEPTED: 202,\r\n  NO_CONTENT: 204,\r\n\r\n  // 3xx Redirection\r\n  MOVED_PERMANENTLY: 301,\r\n  FOUND: 302,\r\n  NOT_MODIFIED: 304,\r\n\r\n  // 4xx Client Errors\r\n  BAD_REQUEST: 400,\r\n  UNAUTHORIZED: 401,\r\n  FORBIDDEN: 403,\r\n  NOT_FOUND: 404,\r\n  CONFLICT: 409,\r\n  UNPROCESSABLE_ENTITY: 422,\r\n  TOO_MANY_REQUESTS: 429,\r\n\r\n  // 5xx Server Errors\r\n  INTERNAL_SERVER_ERROR: 500,\r\n  NOT_IMPLEMENTED: 501,\r\n  BAD_GATEWAY: 502,\r\n  SERVICE_UNAVAILABLE: 503,\r\n  GATEWAY_TIMEOUT: 504\r\n} as const;\r\n\r\nexport type StatusCode = (typeof STATUS_CODES)[keyof typeof STATUS_CODES];\r\n"
                },
                {
                  "type": "file",
                  "path": "src/shared/utils/api-response.ts",
                  "content": "import type { Response } from \"express\";\r\nimport { STATUS_CODES, StatusCode } from \"../constants/status-codes\";\r\n\r\ntype ApiResponseParams<T> = {\r\n  success: boolean;\r\n  message: string;\r\n  statusCode: StatusCode;\r\n  data?: T | null;\r\n  errors?: unknown;\r\n};\r\n\r\nexport class ApiResponse<T = unknown> {\r\n  public readonly success: boolean;\r\n  public readonly message: string;\r\n  public readonly statusCode: StatusCode;\r\n  public readonly data?: T | null;\r\n  public readonly errors?: unknown;\r\n\r\n  constructor({\r\n    success,\r\n    message,\r\n    statusCode,\r\n    data = null,\r\n    errors\r\n  }: ApiResponseParams<T>) {\r\n    this.success = success;\r\n    this.message = message;\r\n    this.statusCode = statusCode;\r\n    this.data = data;\r\n    this.errors = errors;\r\n  }\r\n\r\n  send(res: Response): Response {\r\n    return res.status(this.statusCode).json({\r\n      success: this.success,\r\n      message: this.message,\r\n      statusCode: this.statusCode,\r\n      ...(this.data !== undefined && { data: this.data }),\r\n      ...(this.errors !== undefined && { errors: this.errors })\r\n    });\r\n  }\r\n\r\n  static Success<T>(\r\n    res: Response,\r\n    message: string,\r\n    data?: T,\r\n    statusCode: StatusCode = STATUS_CODES.OK\r\n  ): Response {\r\n    return new ApiResponse<T>({\r\n      success: true,\r\n      message,\r\n      data,\r\n      statusCode\r\n    }).send(res);\r\n  }\r\n\r\n  static ok<T>(res: Response, message = \"OK\", data?: T) {\r\n    return ApiResponse.Success(res, message, data, STATUS_CODES.OK);\r\n  }\r\n\r\n  static created<T>(res: Response, message = \"Created\", data?: T) {\r\n    return ApiResponse.Success(res, message, data, STATUS_CODES.CREATED);\r\n  }\r\n}\r\n\r\n/*\r\n * Usage:\r\n * ApiResponse.ok(res, \"OK\", data);\r\n * ApiResponse.created(res, \"Created\", data);\r\n */\r\n"
                },
                {
                  "type": "file",
                  "path": "src/modules/health/health.routes.ts",
                  "content": "import { Router } from \"express\";\r\nimport { healthCheck, detailedHealthCheck } from \"./health.controller\";\r\n\r\nconst router = Router();\r\n\r\nrouter.get(\"/\", healthCheck);\r\nrouter.get(\"/detailed\", detailedHealthCheck);\r\n\r\nexport default router;\r\n"
                },
                {
                  "type": "file",
                  "path": "src/modules/health/health.controller.ts",
                  "content": "import { Request, Response } from \"express\";\r\nimport { ApiResponse } from \"../../shared/utils/api-response\";\r\n\r\n/**\r\n * Basic health check endpoint\r\n * GET /api/health\r\n */\r\nexport const healthCheck = async (_req: Request, res: Response) => {\r\n  return ApiResponse.Success(res, \"Service is healthy\", {\r\n    status: \"healthy\",\r\n    timestamp: new Date().toISOString(),\r\n    uptime: process.uptime()\r\n  });\r\n};\r\n\r\n/**\r\n * Detailed health check with system information\r\n * GET /api/health/detailed\r\n */\r\nexport const detailedHealthCheck = async (_req: Request, res: Response) => {\r\n  const healthData = {\r\n    status: \"healthy\",\r\n    timestamp: new Date().toISOString(),\r\n    uptime: process.uptime(),\r\n    environment: process.env.NODE_ENV || \"development\",\r\n    version: process.env.npm_package_version || \"1.0.0\",\r\n    memory: {\r\n      used:\r\n        Math.round((process.memoryUsage().heapUsed / 1024 / 1024) * 100) / 100,\r\n      total:\r\n        Math.round((process.memoryUsage().heapTotal / 1024 / 1024) * 100) / 100,\r\n      unit: \"MB\"\r\n    },\r\n    cpu: {\r\n      usage: process.cpuUsage()\r\n    }\r\n  };\r\n\r\n  return ApiResponse.Success(res, \"Service is healthy\", healthData);\r\n};\r\n"
                }
              ]
            }
          }
        }
      }
    }
  }
}
